{
    "id": "DW_43265721",
    "tags": [
        "all",
        "train"
    ],
    "mentions": [
        {
            "begin": 19,
            "end": 28,
            "text": "Antarctic",
            "concept": 6,
            "candidates": [
                "Antarctic",
                "Antarctica",
                "Antarctic_(ship)",
                "Antarctic_Plate",
                "Southern_Ocean",
                "Argentine_Antarctica",
                "Antarctic_Circle",
                "Antarctic_prion",
                "Antarctic_realm",
                "Antarctic_fur_seal",
                "Research_stations_in_Antarctica",
                "Antarctic_ice_sheet",
                "Antarctic_Treaty_System",
                "Antarctic_sea_ice",
                "Chilean_Antarctic_Territory",
                "Polar_climate"
            ],
            "scores": [
                0.7559409120102761,
                0.18304431599229287,
                0.025048169556840076,
                0.007707129094412331,
                0.006422607578676943,
                0.0032113037893384713,
                0.002569043031470777,
                0.0019267822736030828,
                0.0019267822736030828,
                0.0012845215157353885,
                0.0012845215157353885,
                0.0012845215157353885,
                0.0012845215157353885,
                0.0006422607578676942,
                0.0006422607578676942,
                0.0006422607578676942
            ]
        },
        {
            "begin": 51,
            "end": 57,
            "text": "German",
            "concept": 7
        },
        {
            "begin": 148,
            "end": 158,
            "text": "Antarctica",
            "concept": 0,
            "candidates": [
                "Antarctica",
                "Antarctica_(1983_film)",
                "Argentine_Antarctica",
                "Companhia_Antarctica_Paulista",
                "Geography_of_Antarctica",
                "Antarctica_(novel)",
                "Antarctic",
                "Antarctica_(Vangelis_album)",
                "Time_in_Antarctica",
                "History_of_Antarctica",
                "Antarctica_(The_Secret_Handshake_album)",
                "List_of_mammals_of_Antarctica",
                "Territorial_claims_in_Antarctica",
                "Call_signs_in_Antarctica",
                "Antarctic_Plate",
                "Antarctic_ice_sheet"
            ],
            "scores": [
                0.9852205800644516,
                0.002333592621402378,
                0.001333481497944216,
                0.00111123458162018,
                0.001000111123458162,
                0.001000111123458162,
                0.000777864207134126,
                0.000666740748972108,
                0.00055561729081009,
                0.00044449383264807203,
                0.000333370374486054,
                0.000333370374486054,
                0.00022224691632403602,
                0.00022224691632403602,
                0.00022224691632403602,
                0.00022224691632403602
            ]
        },
        {
            "begin": 382,
            "end": 390,
            "text": "EDEN-ISS",
            "concept": 1,
            "candidates": [],
            "scores": []
        },
        {
            "begin": 405,
            "end": 415,
            "text": "Antarctica",
            "concept": 0,
            "candidates": [
                "Antarctica",
                "Antarctica_(1983_film)",
                "Argentine_Antarctica",
                "Companhia_Antarctica_Paulista",
                "Geography_of_Antarctica",
                "Antarctica_(novel)",
                "Antarctic",
                "Antarctica_(Vangelis_album)",
                "Time_in_Antarctica",
                "History_of_Antarctica",
                "Antarctica_(The_Secret_Handshake_album)",
                "List_of_mammals_of_Antarctica",
                "Territorial_claims_in_Antarctica",
                "Call_signs_in_Antarctica",
                "Antarctic_Plate",
                "Antarctic_ice_sheet"
            ],
            "scores": [
                0.9852205800644516,
                0.002333592621402378,
                0.001333481497944216,
                0.00111123458162018,
                0.001000111123458162,
                0.001000111123458162,
                0.000777864207134126,
                0.000666740748972108,
                0.00055561729081009,
                0.00044449383264807203,
                0.000333370374486054,
                0.000333370374486054,
                0.00022224691632403602,
                0.00022224691632403602,
                0.00022224691632403602,
                0.00022224691632403602
            ]
        },
        {
            "begin": 468,
            "end": 470,
            "text": "US",
            "concept": 8,
            "candidates": [
                "United_States",
                "Billboard_200",
                "Billboard_Hot_100",
                "Recording_Industry_Association_of_America",
                "United_States_dollar",
                "Nielsen_SoundScan",
                "Billboard_charts",
                "Hot_Country_Songs",
                "Unincorporated_territories_of_the_United_States",
                "Billboard_(magazine)",
                "Dance_Club_Songs",
                "Federal_government_of_the_United_States",
                "American_English",
                "RIAA_Certification",
                ".us",
                "Us_(Peter_Gabriel_album)"
            ],
            "scores": [
                0.4957150655021834,
                0.22153384279475982,
                0.18400655021834061,
                0.03116812227074236,
                0.012308951965065502,
                0.005676855895196507,
                0.005240174672489083,
                0.0024563318777292577,
                0.0013919213973799126,
                0.0013100436681222707,
                0.0012827510917030568,
                0.0012827510917030568,
                0.001173580786026201,
                0.0011462882096069868,
                0.0011462882096069868,
                0.0011189956331877728
            ]
        },
        {
            "begin": 546,
            "end": 556,
            "text": "Antarctica",
            "concept": 0,
            "candidates": [
                "Antarctica",
                "Antarctica_(1983_film)",
                "Argentine_Antarctica",
                "Companhia_Antarctica_Paulista",
                "Geography_of_Antarctica",
                "Antarctica_(novel)",
                "Antarctic",
                "Antarctica_(Vangelis_album)",
                "Time_in_Antarctica",
                "History_of_Antarctica",
                "Antarctica_(The_Secret_Handshake_album)",
                "List_of_mammals_of_Antarctica",
                "Territorial_claims_in_Antarctica",
                "Call_signs_in_Antarctica",
                "Antarctic_Plate",
                "Antarctic_ice_sheet"
            ],
            "scores": [
                0.9852205800644516,
                0.002333592621402378,
                0.001333481497944216,
                0.00111123458162018,
                0.001000111123458162,
                0.001000111123458162,
                0.000777864207134126,
                0.000666740748972108,
                0.00055561729081009,
                0.00044449383264807203,
                0.000333370374486054,
                0.000333370374486054,
                0.00022224691632403602,
                0.00022224691632403602,
                0.00022224691632403602,
                0.00022224691632403602
            ]
        },
        {
            "begin": 689,
            "end": 712,
            "text": "German Aerospace Center",
            "concept": 3,
            "candidates": [
                "German_Aerospace_Center"
            ],
            "scores": [
                1.0
            ]
        },
        {
            "begin": 714,
            "end": 717,
            "text": "DLR",
            "concept": 3,
            "candidates": [
                "German_Aerospace_Center",
                "Docklands_Light_Railway",
                "Debout_la_France",
                "Drug_Law_Reform_Australia",
                "DLR_Institute_for_Planetary_Research",
                "Defender_(association_football)",
                "Kunming_Ruilong_F.C.",
                "D\u00fan_Laoghaire\u2013Rathdown",
                "Dansk_Landbrugs_Realkreditfond",
                "DLR_Group",
                "Deutschlandradio",
                "DLR",
                "Dynamic_Language_Runtime"
            ],
            "scores": [
                0.47648902821316613,
                0.3103448275862069,
                0.109717868338558,
                0.05642633228840126,
                0.01567398119122257,
                0.006269592476489028,
                0.006269592476489028,
                0.003134796238244514,
                0.003134796238244514,
                0.003134796238244514,
                0.003134796238244514,
                0.003134796238244514,
                0.003134796238244514
            ]
        },
        {
            "begin": 763,
            "end": 767,
            "text": "Mars",
            "concept": 9,
            "candidates": [
                "Mars",
                "Mars_(mythology)",
                "Mars,_Incorporated",
                "Mars_(astrology)",
                "Cheung_Wing_Fat",
                "Mid-Atlantic_Regional_Spaceport",
                "Mars_(band)",
                "Mars_(Philippine_talk_show)",
                "Mars_(2016_TV_series)",
                "Mars,_Pennsylvania",
                "Mars_(rapper)",
                "Mars_(chocolate_bar)",
                "Mars_in_fiction",
                "Colonization_of_Mars",
                "Mars_(manga)",
                "Mars_(Doctor_Who)"
            ],
            "scores": [
                0.7393899204244032,
                0.10908488063660478,
                0.023375331564986737,
                0.016744031830238728,
                0.01276525198938992,
                0.005802387267904509,
                0.005636604774535809,
                0.005470822281167109,
                0.004973474801061008,
                0.0044761273209549075,
                0.004144562334217507,
                0.003647214854111406,
                0.0031498673740053052,
                0.002652519893899204,
                0.002486737400530504,
                0.002486737400530504
            ]
        },
        {
            "begin": 850,
            "end": 860,
            "text": "Antarctica",
            "concept": 0,
            "candidates": [
                "Antarctica",
                "Antarctica_(1983_film)",
                "Argentine_Antarctica",
                "Companhia_Antarctica_Paulista",
                "Geography_of_Antarctica",
                "Antarctica_(novel)",
                "Antarctic",
                "Antarctica_(Vangelis_album)",
                "Time_in_Antarctica",
                "History_of_Antarctica",
                "Antarctica_(The_Secret_Handshake_album)",
                "List_of_mammals_of_Antarctica",
                "Territorial_claims_in_Antarctica",
                "Call_signs_in_Antarctica",
                "Antarctic_Plate",
                "Antarctic_ice_sheet"
            ],
            "scores": [
                0.9852205800644516,
                0.002333592621402378,
                0.001333481497944216,
                0.00111123458162018,
                0.001000111123458162,
                0.001000111123458162,
                0.000777864207134126,
                0.000666740748972108,
                0.00055561729081009,
                0.00044449383264807203,
                0.000333370374486054,
                0.000333370374486054,
                0.00022224691632403602,
                0.00022224691632403602,
                0.00022224691632403602,
                0.00022224691632403602
            ]
        },
        {
            "begin": 890,
            "end": 893,
            "text": "DLR",
            "concept": 3,
            "candidates": [
                "German_Aerospace_Center",
                "Docklands_Light_Railway",
                "Debout_la_France",
                "Drug_Law_Reform_Australia",
                "DLR_Institute_for_Planetary_Research",
                "Defender_(association_football)",
                "Kunming_Ruilong_F.C.",
                "D\u00fan_Laoghaire\u2013Rathdown",
                "Dansk_Landbrugs_Realkreditfond",
                "DLR_Group",
                "Deutschlandradio",
                "DLR",
                "Dynamic_Language_Runtime"
            ],
            "scores": [
                0.47648902821316613,
                0.3103448275862069,
                0.109717868338558,
                0.05642633228840126,
                0.01567398119122257,
                0.006269592476489028,
                0.006269592476489028,
                0.003134796238244514,
                0.003134796238244514,
                0.003134796238244514,
                0.003134796238244514,
                0.003134796238244514,
                0.003134796238244514
            ]
        },
        {
            "begin": 907,
            "end": 916,
            "text": "Antarctic",
            "concept": 6,
            "candidates": [
                "Antarctic",
                "Antarctica",
                "Antarctic_(ship)",
                "Antarctic_Plate",
                "Southern_Ocean",
                "Argentine_Antarctica",
                "Antarctic_Circle",
                "Antarctic_prion",
                "Antarctic_realm",
                "Antarctic_fur_seal",
                "Research_stations_in_Antarctica",
                "Antarctic_ice_sheet",
                "Antarctic_Treaty_System",
                "Antarctic_sea_ice",
                "Chilean_Antarctic_Territory",
                "Polar_climate"
            ],
            "scores": [
                0.7559409120102761,
                0.18304431599229287,
                0.025048169556840076,
                0.007707129094412331,
                0.006422607578676943,
                0.0032113037893384713,
                0.002569043031470777,
                0.0019267822736030828,
                0.0019267822736030828,
                0.0012845215157353885,
                0.0012845215157353885,
                0.0012845215157353885,
                0.0012845215157353885,
                0.0006422607578676942,
                0.0006422607578676942,
                0.0006422607578676942
            ]
        },
        {
            "begin": 917,
            "end": 925,
            "text": "gardener",
            "concept": 10
        },
        {
            "begin": 926,
            "end": 936,
            "text": "Paul Zabel",
            "concept": 4,
            "candidates": [],
            "scores": []
        },
        {
            "begin": 1076,
            "end": 1085,
            "text": "Antarctic",
            "concept": 6,
            "candidates": [
                "Antarctic",
                "Antarctica",
                "Antarctic_(ship)",
                "Antarctic_Plate",
                "Southern_Ocean",
                "Argentine_Antarctica",
                "Antarctic_Circle",
                "Antarctic_prion",
                "Antarctic_realm",
                "Antarctic_fur_seal",
                "Research_stations_in_Antarctica",
                "Antarctic_ice_sheet",
                "Antarctic_Treaty_System",
                "Antarctic_sea_ice",
                "Chilean_Antarctic_Territory",
                "Polar_climate"
            ],
            "scores": [
                0.7559409120102761,
                0.18304431599229287,
                0.025048169556840076,
                0.007707129094412331,
                0.006422607578676943,
                0.0032113037893384713,
                0.002569043031470777,
                0.0019267822736030828,
                0.0019267822736030828,
                0.0012845215157353885,
                0.0012845215157353885,
                0.0012845215157353885,
                0.0012845215157353885,
                0.0006422607578676942,
                0.0006422607578676942,
                0.0006422607578676942
            ]
        },
        {
            "begin": 1125,
            "end": 1133,
            "text": "February",
            "concept": 11
        },
        {
            "begin": 1256,
            "end": 1261,
            "text": "Zabel",
            "concept": 4,
            "candidates": [
                "Zabel_(engine)",
                "Isabella,_Queen_of_Armenia",
                "Rick_Zabel",
                "Erik_Zabel",
                "Hermann_Zabel"
            ],
            "scores": [
                0.8571428571428571,
                0.061224489795918366,
                0.04081632653061224,
                0.02040816326530612,
                0.02040816326530612
            ]
        },
        {
            "begin": 1340,
            "end": 1350,
            "text": "Antarctica",
            "concept": 0,
            "candidates": [
                "Antarctica",
                "Antarctica_(1983_film)",
                "Argentine_Antarctica",
                "Companhia_Antarctica_Paulista",
                "Geography_of_Antarctica",
                "Antarctica_(novel)",
                "Antarctic",
                "Antarctica_(Vangelis_album)",
                "Time_in_Antarctica",
                "History_of_Antarctica",
                "Antarctica_(The_Secret_Handshake_album)",
                "List_of_mammals_of_Antarctica",
                "Territorial_claims_in_Antarctica",
                "Call_signs_in_Antarctica",
                "Antarctic_Plate",
                "Antarctic_ice_sheet"
            ],
            "scores": [
                0.9852205800644516,
                0.002333592621402378,
                0.001333481497944216,
                0.00111123458162018,
                0.001000111123458162,
                0.001000111123458162,
                0.000777864207134126,
                0.000666740748972108,
                0.00055561729081009,
                0.00044449383264807203,
                0.000333370374486054,
                0.000333370374486054,
                0.00022224691632403602,
                0.00022224691632403602,
                0.00022224691632403602,
                0.00022224691632403602
            ]
        },
        {
            "begin": 1501,
            "end": 1511,
            "text": "Antarctica",
            "concept": 0,
            "candidates": [
                "Antarctica",
                "Antarctica_(1983_film)",
                "Argentine_Antarctica",
                "Companhia_Antarctica_Paulista",
                "Geography_of_Antarctica",
                "Antarctica_(novel)",
                "Antarctic",
                "Antarctica_(Vangelis_album)",
                "Time_in_Antarctica",
                "History_of_Antarctica",
                "Antarctica_(The_Secret_Handshake_album)",
                "List_of_mammals_of_Antarctica",
                "Territorial_claims_in_Antarctica",
                "Call_signs_in_Antarctica",
                "Antarctic_Plate",
                "Antarctic_ice_sheet"
            ],
            "scores": [
                0.9852205800644516,
                0.002333592621402378,
                0.001333481497944216,
                0.00111123458162018,
                0.001000111123458162,
                0.001000111123458162,
                0.000777864207134126,
                0.000666740748972108,
                0.00055561729081009,
                0.00044449383264807203,
                0.000333370374486054,
                0.000333370374486054,
                0.00022224691632403602,
                0.00022224691632403602,
                0.00022224691632403602,
                0.00022224691632403602
            ]
        },
        {
            "begin": 1559,
            "end": 1574,
            "text": "project manager",
            "concept": 12
        },
        {
            "begin": 1575,
            "end": 1590,
            "text": "Daniel Schubert",
            "concept": 5,
            "candidates": [],
            "scores": []
        },
        {
            "begin": 1795,
            "end": 1803,
            "text": "Schubert",
            "concept": 5,
            "candidates": [
                "Franz_Schubert",
                "Electoral_district_of_Schubert",
                "Jakob_Schubert",
                "Schubert_(lunar_crater)",
                "Schubert,_Pennsylvania",
                "Schubert_Motorsport",
                "Albrecht_Schubert",
                "Heinz_Schubert_(SS_officer)",
                "Fran\u00e7ois_Schubert",
                "Fabian_Schubert",
                "Schubert_(surname)",
                "Ave_Maria_(Schubert)",
                "HTC_HD7",
                "Shubert_Theatre_(New_York_City)",
                "Friedrich_Schubert",
                "Schubert_(disambiguation)"
            ],
            "scores": [
                0.9498257839721255,
                0.023693379790940768,
                0.005574912891986063,
                0.005574912891986063,
                0.004878048780487805,
                0.0020905923344947735,
                0.0013937282229965157,
                0.0006968641114982578,
                0.0006968641114982578,
                0.0006968641114982578,
                0.0006968641114982578,
                0.0006968641114982578,
                0.0006968641114982578,
                0.0006968641114982578,
                0.0006968641114982578,
                0.0006968641114982578
            ]
        },
        {
            "begin": 1986,
            "end": 2010,
            "text": "Alfred Wegener Institute",
            "concept": 13,
            "candidates": [
                "Alfred_Wegener_Institute_for_Polar_and_Marine_Research"
            ],
            "scores": [
                1.0
            ]
        },
        {
            "begin": 2091,
            "end": 2111,
            "text": "Neumeyer Station III",
            "concept": 2,
            "candidates": [],
            "scores": []
        },
        {
            "begin": 2194,
            "end": 2214,
            "text": "Neumeyer Station III",
            "concept": 2,
            "candidates": [],
            "scores": []
        },
        {
            "begin": 2223,
            "end": 2232,
            "text": "Antarctic",
            "concept": 6,
            "candidates": [
                "Antarctic",
                "Antarctica",
                "Antarctic_(ship)",
                "Antarctic_Plate",
                "Southern_Ocean",
                "Argentine_Antarctica",
                "Antarctic_Circle",
                "Antarctic_prion",
                "Antarctic_realm",
                "Antarctic_fur_seal",
                "Research_stations_in_Antarctica",
                "Antarctic_ice_sheet",
                "Antarctic_Treaty_System",
                "Antarctic_sea_ice",
                "Chilean_Antarctic_Territory",
                "Polar_climate"
            ],
            "scores": [
                0.7559409120102761,
                0.18304431599229287,
                0.025048169556840076,
                0.007707129094412331,
                0.006422607578676943,
                0.0032113037893384713,
                0.002569043031470777,
                0.0019267822736030828,
                0.0019267822736030828,
                0.0012845215157353885,
                0.0012845215157353885,
                0.0012845215157353885,
                0.0012845215157353885,
                0.0006422607578676942,
                0.0006422607578676942,
                0.0006422607578676942
            ]
        },
        {
            "begin": 2319,
            "end": 2327,
            "text": "February",
            "concept": 11
        },
        {
            "begin": 2406,
            "end": 2416,
            "text": "Antarctica",
            "concept": 0,
            "candidates": [
                "Antarctica",
                "Antarctica_(1983_film)",
                "Argentine_Antarctica",
                "Companhia_Antarctica_Paulista",
                "Geography_of_Antarctica",
                "Antarctica_(novel)",
                "Antarctic",
                "Antarctica_(Vangelis_album)",
                "Time_in_Antarctica",
                "History_of_Antarctica",
                "Antarctica_(The_Secret_Handshake_album)",
                "List_of_mammals_of_Antarctica",
                "Territorial_claims_in_Antarctica",
                "Call_signs_in_Antarctica",
                "Antarctic_Plate",
                "Antarctic_ice_sheet"
            ],
            "scores": [
                0.9852205800644516,
                0.002333592621402378,
                0.001333481497944216,
                0.00111123458162018,
                0.001000111123458162,
                0.001000111123458162,
                0.000777864207134126,
                0.000666740748972108,
                0.00055561729081009,
                0.00044449383264807203,
                0.000333370374486054,
                0.000333370374486054,
                0.00022224691632403602,
                0.00022224691632403602,
                0.00022224691632403602,
                0.00022224691632403602
            ]
        },
        {
            "begin": 2424,
            "end": 2439,
            "text": "station manager",
            "concept": 14
        },
        {
            "begin": 2440,
            "end": 2454,
            "text": "Bernhard Gropp",
            "concept": 15,
            "candidates": [],
            "scores": []
        },
        {
            "begin": 2532,
            "end": 2542,
            "text": "06.04.2018",
            "concept": 16
        },
        {
            "begin": 2663,
            "end": 2673,
            "text": "Antarctica",
            "concept": 0,
            "candidates": [
                "Antarctica",
                "Antarctica_(1983_film)",
                "Argentine_Antarctica",
                "Companhia_Antarctica_Paulista",
                "Geography_of_Antarctica",
                "Antarctica_(novel)",
                "Antarctic",
                "Antarctica_(Vangelis_album)",
                "Time_in_Antarctica",
                "History_of_Antarctica",
                "Antarctica_(The_Secret_Handshake_album)",
                "List_of_mammals_of_Antarctica",
                "Territorial_claims_in_Antarctica",
                "Call_signs_in_Antarctica",
                "Antarctic_Plate",
                "Antarctic_ice_sheet"
            ],
            "scores": [
                0.9852205800644516,
                0.002333592621402378,
                0.001333481497944216,
                0.00111123458162018,
                0.001000111123458162,
                0.001000111123458162,
                0.000777864207134126,
                0.000666740748972108,
                0.00055561729081009,
                0.00044449383264807203,
                0.000333370374486054,
                0.000333370374486054,
                0.00022224691632403602,
                0.00022224691632403602,
                0.00022224691632403602,
                0.00022224691632403602
            ]
        },
        {
            "begin": 2749,
            "end": 2772,
            "text": "German Aerospace Center",
            "concept": 3,
            "candidates": [
                "German_Aerospace_Center"
            ],
            "scores": [
                1.0
            ]
        },
        {
            "begin": 2786,
            "end": 2801,
            "text": "McMurdo Station",
            "concept": 17,
            "candidates": [
                "McMurdo_Station"
            ],
            "scores": [
                1.0
            ]
        },
        {
            "begin": 2806,
            "end": 2839,
            "text": "Amundsen-Scott South Pole Station",
            "concept": 18,
            "candidates": [
                "Amundsen\u2013Scott_South_Pole_Station"
            ],
            "scores": [
                1.0
            ]
        },
        {
            "begin": 2910,
            "end": 2925,
            "text": "McMurdo Station",
            "concept": 17,
            "candidates": [
                "McMurdo_Station"
            ],
            "scores": [
                1.0
            ]
        },
        {
            "begin": 2942,
            "end": 2946,
            "text": "1980",
            "concept": 19
        },
        {
            "begin": 2993,
            "end": 3001,
            "text": "1830 UTC",
            "concept": 20
        },
        {
            "begin": 3003,
            "end": 3005,
            "text": "DW",
            "concept": 21,
            "candidates": [
                "Drum_Workshop",
                "Deutsche_Welle",
                "DW-TV",
                "Defender_(association_football)",
                "Dreamworld_(Australian_theme_park)",
                "Data_warehouse",
                "Delhi_Wizards",
                "D.W._Read",
                "DW",
                "Discworld"
            ],
            "scores": [
                0.6717557251908397,
                0.17557251908396945,
                0.03816793893129771,
                0.022900763358778626,
                0.022900763358778626,
                0.022900763358778626,
                0.015267175572519083,
                0.015267175572519083,
                0.007633587786259542,
                0.007633587786259542
            ]
        }
    ],
    "concepts": [
        {
            "concept": 0,
            "text": "Antarctica",
            "keyword": true,
            "count": 8,
            "link": "Antarctica",
            "tags": [
                "slot::keyword",
                "topic::none",
                "type::entity",
                "type::location",
                "type::regio"
            ]
        },
        {
            "concept": 1,
            "text": "EDEN-ISS",
            "keyword": true,
            "count": 1,
            "link": null,
            "tags": [
                "meta::todo",
                "slot::keyword",
                "topic::none",
                "type::entity",
                "type::misc"
            ]
        },
        {
            "concept": 2,
            "text": "Neumeyer Station III",
            "keyword": true,
            "count": 2,
            "link": "Neumayer-Station_III",
            "tags": [
                "slot::keyword",
                "type::entity",
                "type::facility",
                "type::location"
            ]
        },
        {
            "concept": 3,
            "text": "German Aerospace Center",
            "keyword": true,
            "count": 4,
            "link": "German_Aerospace_Center",
            "tags": [
                "iptc::11000000",
                "slot::keyword",
                "topic::politics",
                "type::agency",
                "type::entity",
                "type::governmental_organisation",
                "type::organization"
            ]
        },
        {
            "concept": 4,
            "text": "Paul Zabel",
            "keyword": true,
            "count": 2,
            "link": null,
            "tags": [
                "gender::male",
                "iptc::13000000",
                "slot::keyword",
                "topic::science",
                "type::entity",
                "type::person",
                "type::science_per"
            ]
        },
        {
            "concept": 5,
            "text": "Daniel Schubert",
            "keyword": true,
            "count": 3,
            "link": null,
            "tags": [
                "gender::male",
                "iptc::13000000",
                "slot::head",
                "slot::keyword",
                "topic::science",
                "type::entity",
                "type::person",
                "type::science_per"
            ]
        },
        {
            "concept": 6,
            "text": "Antarctic",
            "keyword": false,
            "count": 4,
            "link": "Antarctic",
            "tags": [
                "topic::none",
                "type::entity",
                "type::location",
                "type::regio"
            ]
        },
        {
            "concept": 7,
            "text": "German",
            "keyword": false,
            "count": 1,
            "tags": [
                "topic::none",
                "type::gpe0-x",
                "type::other"
            ]
        },
        {
            "concept": 8,
            "text": "US",
            "keyword": false,
            "count": 1,
            "link": "United_States",
            "tags": [
                "topic::none",
                "type::entity",
                "type::gpe",
                "type::gpe0",
                "type::location"
            ]
        },
        {
            "concept": 9,
            "text": "Mars",
            "keyword": false,
            "count": 1,
            "link": "Mars",
            "tags": [
                "topic::none",
                "type::celestial_loc",
                "type::entity",
                "type::location"
            ]
        },
        {
            "concept": 10,
            "text": "gardener",
            "keyword": false,
            "count": 1,
            "tags": [
                "topic::none",
                "type::role",
                "type::value"
            ]
        },
        {
            "concept": 11,
            "text": "February",
            "keyword": false,
            "count": 2,
            "tags": [
                "topic::none",
                "type::time",
                "type::value"
            ]
        },
        {
            "concept": 12,
            "text": "project manager",
            "keyword": false,
            "count": 1,
            "tags": [
                "topic::none",
                "type::role",
                "type::value"
            ]
        },
        {
            "concept": 13,
            "text": "Alfred Wegener Institute",
            "keyword": false,
            "count": 1,
            "link": "Alfred_Wegener_Institute_for_Polar_and_Marine_Research",
            "tags": [
                "iptc::05000000",
                "topic::education",
                "type::education_org",
                "type::entity",
                "type::organization"
            ]
        },
        {
            "concept": 14,
            "text": "station manager",
            "keyword": false,
            "count": 1,
            "tags": [
                "topic::none",
                "type::role",
                "type::value"
            ]
        },
        {
            "concept": 15,
            "text": "Bernhard Gropp",
            "keyword": false,
            "count": 1,
            "link": null,
            "tags": [
                "gender::male",
                "iptc::13000000",
                "slot::head",
                "topic::science",
                "type::entity",
                "type::person",
                "type::science_per"
            ]
        },
        {
            "concept": 16,
            "text": "06.04.2018",
            "keyword": false,
            "count": 1,
            "tags": [
                "topic::none",
                "type::time",
                "type::value"
            ]
        },
        {
            "concept": 17,
            "text": "McMurdo Station",
            "keyword": false,
            "count": 2,
            "link": "McMurdo_Station",
            "tags": [
                "type::entity",
                "type::facility",
                "type::location"
            ]
        },
        {
            "concept": 18,
            "text": "Amundsen-Scott South Pole Station",
            "keyword": false,
            "count": 1,
            "link": "Amundsen\u2013Scott_South_Pole_Station",
            "tags": [
                "type::entity",
                "type::facility",
                "type::location"
            ]
        },
        {
            "concept": 19,
            "text": "1980",
            "keyword": false,
            "count": 1,
            "tags": [
                "topic::none",
                "type::time",
                "type::value"
            ]
        },
        {
            "concept": 20,
            "text": "1830 UTC",
            "keyword": false,
            "count": 1,
            "tags": [
                "topic::none",
                "type::time",
                "type::value"
            ]
        },
        {
            "concept": 21,
            "text": "DW",
            "keyword": false,
            "count": 1,
            "link": "Deutsche_Welle",
            "tags": [
                "topic::media",
                "type::entity",
                "type::media",
                "type::organization"
            ]
        },
        {
            "concept": 22,
            "keyword": false,
            "count": 0,
            "link": "Germany",
            "tags": []
        }
    ],
    "relations": [
        {
            "s": 3,
            "p": "agency_of",
            "o": 22
        },
        {
            "s": 3,
            "p": "agency_of-x",
            "o": 7
        },
        {
            "s": 3,
            "p": "based_in0",
            "o": 22
        },
        {
            "s": 3,
            "p": "based_in0-x",
            "o": 7
        },
        {
            "s": 4,
            "p": "citizen_of",
            "o": 22
        },
        {
            "s": 4,
            "p": "citizen_of-x",
            "o": 7
        },
        {
            "s": 4,
            "p": "member_of",
            "o": 3
        },
        {
            "s": 5,
            "p": "citizen_of",
            "o": 22
        },
        {
            "s": 5,
            "p": "citizen_of-x",
            "o": 7
        },
        {
            "s": 5,
            "p": "head_of",
            "o": 3
        },
        {
            "s": 5,
            "p": "member_of",
            "o": 3
        },
        {
            "s": 7,
            "p": "gpe0",
            "o": 22
        },
        {
            "s": 13,
            "p": "based_in0",
            "o": 22
        },
        {
            "s": 13,
            "p": "based_in0-x",
            "o": 7
        },
        {
            "s": 15,
            "p": "citizen_of",
            "o": 22
        },
        {
            "s": 15,
            "p": "citizen_of-x",
            "o": 7
        },
        {
            "s": 15,
            "p": "head_of",
            "o": 2
        },
        {
            "s": 15,
            "p": "member_of",
            "o": 2
        },
        {
            "s": 21,
            "p": "based_in0",
            "o": 22
        },
        {
            "s": 21,
            "p": "based_in0-x",
            "o": 7
        }
    ],
    "frames": [
        {
            "type": "none",
            "slots": [
                {
                    "name": "place",
                    "value": 0
                }
            ]
        }
    ],
    "iptc": [
        "04000000",
        "20000170",
        "20000192",
        "20000208"
    ]
}